revornix/__init__.py
revornix/core.py
revornix/api/__init__.py
revornix/api/document.py
revornix/api/file.py
revornix/api/section.py
revornix/schema/__init__.py
revornix/schema/common.py
revornix/schema/document.py
revornix/schema/file.py
revornix/schema/section.py
revornix-0.0.7.dist-info/licenses/LICENSE
revornix-0.0.7.dist-info/METADATA
revornix-0.0.7.dist-info/WHEEL
revornix-0.0.7.dist-info/top_level.txt
revornix-0.0.7.dist-info/RECORD
