Metadata-Version: 2.4
Name: revornix
Version: 0.0.7
Summary: The python package for Revornix API.
Author-email: Kinda Hall <1142704468@qq.com>
Project-URL: Homepage, https://github.com/Qingyon-AI/Revornix-Python-Lib
Requires-Python: >=3.10
License-File: LICENSE
Requires-Dist: httpx
Requires-Dist: pydantic>=2.0
Provides-Extra: test
Requires-Dist: pytest; extra == "test"
Dynamic: license-file
